qc_quad/__init__.py
qc_quad/gauss_lebedev_ball.py
qc_quad/gauss_legendre.py
qc_quad/lebedev/__init__.py
qc_quad/lebedev/gen_oh.py
qc_quad/lebedev/llq.py
qc_quad/lebedev/llq_all.py
qc_quad/lebedev/utils/__init__.py
qc_quad/lebedev/utils/code_generation.py
qc_quad-0.1.1.dist-info/LICENSE
qc_quad-0.1.1.dist-info/WHEEL
qc_quad-0.1.1.dist-info/METADATA
qc_quad-0.1.1.dist-info/RECORD
