Metadata-Version: 2.1
Name: qc-quad
Version: 0.1.1
Summary: Quantum-chemistry quadrature package
License: MIT
Author: Peter Koval
Author-email: koval.peter@gmail.com
Requires-Python: >=3.9,<4.0
Classifier: License :: OSI Approved :: MIT License
Classifier: Programming Language :: Python :: 3
Classifier: Programming Language :: Python :: 3.9
Classifier: Programming Language :: Python :: 3.10
Classifier: Programming Language :: Python :: 3.11
Requires-Dist: numpy (>=1.24.0,<2.0.0)
